hermes_toml/__init__.py
hermes_toml/harvest.py
hermes_plugin_python-0.2.0.dist-info/METADATA
hermes_plugin_python-0.2.0.dist-info/WHEEL
hermes_plugin_python-0.2.0.dist-info/entry_points.txt
hermes_plugin_python-0.2.0.dist-info/top_level.txt
hermes_plugin_python-0.2.0.dist-info/RECORD
