Metadata-Version: 2.1
Name: hermes-plugin-python
Version: 0.2.0
Summary: HERMES plugin for .toml files
Author: Michael Fritzsche
Author-email: Michael Meinel <michael.meinel@dlr.de>
License: Apache-2.0
Project-URL: Repository, https://github.com/hermes-hmc/hermes-plugin-python
Keywords: publishing,metadata,automation
Classifier: Development Status :: 2 - Pre-Alpha
Classifier: Environment :: Plugins
Classifier: Programming Language :: Python :: 3
Classifier: Operating System :: OS Independent
Requires-Python: >=3.8
Requires-Dist: hermes >=0.8.0
Provides-Extra: dev
Requires-Dist: pytest >=8.2.2 ; extra == 'dev'
Requires-Dist: pytest-cov >=3.0.0 ; extra == 'dev'
Requires-Dist: taskipy >=1.10.3 ; extra == 'dev'
Requires-Dist: flake8 >=5.0.4 ; extra == 'dev'
Requires-Dist: reuse >=1.1.2 ; extra == 'dev'
